MANIFEST.in
README.md
markdown_test.md
setup.py
dfsummarizer/FlajoletMartin.py
dfsummarizer/__init__.py
dfsummarizer/__main__.py
dfsummarizer/config.py
dfsummarizer/dfsummarizer.py
dfsummarizer/funcs.py
dfsummarizer.egg-info/PKG-INFO
dfsummarizer.egg-info/SOURCES.txt
dfsummarizer.egg-info/dependency_links.txt
dfsummarizer.egg-info/entry_points.txt
dfsummarizer.egg-info/requires.txt
dfsummarizer.egg-info/top_level.txt