Metadata-Version: 2.1
Name: dfsummarizer
Version: 0.1.4
Summary: Python command line application to summarize a CSV or TSV dataset.
Home-page: http://john-hawkins.github.io
Author: John Hawkins
Author-email: hawkins.john.c@gmail.com
License: MIT
Project-URL: Documentation, http://john-hawkins.github.io
Project-URL: Source, https://github.com/john-hawkins/dfsummarizer
Project-URL: Tracker, https://github.com/john-hawkins/dfsummarizer/issues
Platform: UNKNOWN
